jobstack/__init__.py
jobstack/app.py
jobstack/calendar.py
jobstack/colors.py
jobstack/common.py
jobstack/data.py
jobstack/project.py
jobstack/resources/__init__.py
jobstack/resources/base.html
jobstack/resources/calendar.css
jobstack/resources/calendar.html
jobstack/resources/calendar.js
jobstack/resources/preamble.html
jobstack/resources/project_list.html
jobstack/structs.py
jobstack-0.1.1.dist-info/entry_points.txt
jobstack-0.1.1.dist-info/WHEEL
jobstack-0.1.1.dist-info/METADATA
jobstack-0.1.1.dist-info/RECORD
