Metadata-Version: 2.1
Name: jobstack
Version: 0.1.1
Summary: Commandline utility for organizing and scheduling project tasks across a team.
License: MIT
Author: Mark Gemmill
Author-email: mark@markgemmill.com
Requires-Python: >=3.7,<4.0
Classifier: Development Status :: 3 - Alpha
Classifier: Environment :: Console
Classifier: License :: OSI Approved :: MIT License
Classifier: Programming Language :: Python :: 3
Classifier: Programming Language :: Python :: 3.7
Requires-Dist: docopt (>=0.6.2,<0.7.0)
Requires-Dist: jinja2 (>=2.10,<3.0)
Requires-Dist: pendulum (>=2.0,<3.0)
